aiflux/__init__.py
aiflux/benchmark_utils.py
aiflux/cli.py
aiflux/container/container.def
aiflux/converters/__init__.py
aiflux/converters/csv.py
aiflux/converters/directory.py
aiflux/converters/json.py
aiflux/converters/utils.py
aiflux/converters/vision.py
aiflux/core/__init__.py
aiflux/core/client.py
aiflux/core/config.py
aiflux/core/config_manager.py
aiflux/core/processor.py
aiflux/io/__init__.py
aiflux/io/base.py
aiflux/io/input/__init__.py
aiflux/io/output/__init__.py
aiflux/io/output/json_output.py
aiflux/processors/__init__.py
aiflux/processors/batch.py
aiflux/slurm/__init__.py
aiflux/slurm/runner.py
llmflux-0.1.1.dist-info/licenses/LICENSE
llmflux-0.1.1.dist-info/METADATA
llmflux-0.1.1.dist-info/WHEEL
llmflux-0.1.1.dist-info/entry_points.txt
llmflux-0.1.1.dist-info/top_level.txt
llmflux-0.1.1.dist-info/RECORD
